hoopy/__init__.py
hoopy/__main__.py
hoopy/codec.py
hoopy/infix.py
hoopy/magic.py
hoopy/runtime.py
hoopy/tokens.py
hoopy/transform.py
hoopy/utils.py
hoopy-1.1.1.dist-info/METADATA
hoopy-1.1.1.dist-info/WHEEL
hoopy-1.1.1.dist-info/RECORD
