Metadata-Version: 2.1
Name: hoopy
Version: 1.1.1
Summary: 
Author: Olivia Palmu
Author-email: hiemankaranteenissa@proton.me
Requires-Python: >=3.10,<4.0
Classifier: Programming Language :: Python :: 3
Classifier: Programming Language :: Python :: 3.10
Classifier: Programming Language :: Python :: 3.11
Classifier: Programming Language :: Python :: 3.12
